model2data/__init__.py
model2data/cli.py
model2data/utils.py
model2data/dbt/__init__.py
model2data/dbt/project.py
model2data/dbt/tests.py
model2data/dbt/templates/dbt_project.yml.jinja
model2data/dbt/templates/profiles.yml.jinja
model2data/dbt/templates/macros/generate_schema_name.sql
model2data/generate/__init__.py
model2data/generate/core.py
model2data/generate/faker.py
model2data/generate/relationships.py
model2data/parse/__init__.py
model2data/parse/dbml.py
model2data-0.2.3.dist-info/licenses/LICENSE
model2data-0.2.3.dist-info/METADATA
model2data-0.2.3.dist-info/WHEEL
model2data-0.2.3.dist-info/entry_points.txt
model2data-0.2.3.dist-info/top_level.txt
model2data-0.2.3.dist-info/RECORD
