Metadata-Version: 2.4
Name: model2data
Version: 0.2.3
Summary: Generate analytics-ready datasets from DBML models
Requires-Python: >=3.10
License-File: LICENSE
Requires-Dist: dbt-core>=1.5.0
Requires-Dist: dbt-duckdb>=1.5.0
Requires-Dist: faker>=37.12.0
Requires-Dist: pandas>=2.3.3
Requires-Dist: pyyaml>=6.0.3
Requires-Dist: typer>=0.20.0
Provides-Extra: dev
Requires-Dist: pytest; extra == "dev"
Requires-Dist: pytest-cov; extra == "dev"
Requires-Dist: pre-commit; extra == "dev"
Requires-Dist: ruff>=0.1.0; extra == "dev"
Requires-Dist: black>=23.0.0; extra == "dev"
Requires-Dist: ty>=0.0.4; extra == "dev"
Requires-Dist: types-pyyaml; extra == "dev"
Requires-Dist: poethepoet>=0.38.0; extra == "dev"
Dynamic: license-file
